rnr/__init__.py
rnr/__main__.py
rnr/bookmarks.py
rnr/buttonbar.py
rnr/cmdbar.py
rnr/config.py
rnr/database.py
rnr/debug_print.py
rnr/dlg_cancelable.py
rnr/dlg_cpmv.py
rnr/dlg_cpmv_progress.py
rnr/dlg_delete_progress.py
rnr/dlg_dirscan.py
rnr/dlg_error.py
rnr/dlg_goto.py
rnr/dlg_pending_job.py
rnr/dlg_question.py
rnr/dlg_report.py
rnr/dlg_search.py
rnr/fallocate.py
rnr/import_config.py
rnr/palette.py
rnr/panel.py
rnr/preview_panel.py
rnr/rnr_cpmv.py
rnr/rnr_delete.py
rnr/rnr_dirscan.py
rnr/rnrview.py
rnr/utils.py
rnr-1.0.10.data/data/share/man/man1/rnr.1
rnr-1.0.10.data/data/share/man/man1/rnrview.1
rnr-1.0.10.data/data/share/rnr/rnr.fish
rnr-1.0.10.data/data/share/rnr/rnr.sh
rnr-1.0.10.dist-info/AUTHORS
rnr-1.0.10.dist-info/LICENSE
rnr-1.0.10.dist-info/METADATA
rnr-1.0.10.dist-info/WHEEL
rnr-1.0.10.dist-info/entry_points.txt
rnr-1.0.10.dist-info/top_level.txt
rnr-1.0.10.dist-info/RECORD
