Metadata-Version: 2.1
Name: rnr
Version: 1.0.10
Summary: The RNR File Manager (RNR's Not Ranger)
Home-page: https://github.com/bugnano/rnr
Author: Franco Bugnano
Author-email: franco@bugnano.it
License: UNKNOWN
Platform: UNKNOWN
Classifier: Development Status :: 5 - Production/Stable
Classifier: Environment :: Console :: Curses
Classifier: Intended Audience :: End Users/Desktop
Classifier: Intended Audience :: System Administrators
Classifier: License :: OSI Approved :: GNU General Public License v3 or later (GPLv3+)
Classifier: Natural Language :: English
Classifier: Operating System :: POSIX :: Linux
Classifier: Programming Language :: Python :: 3
Classifier: Topic :: Desktop Environment :: File Managers
Classifier: Topic :: System
Classifier: Topic :: System :: Systems Administration
Classifier: Topic :: Utilities
Requires-Python: >=3.6
License-File: LICENSE
License-File: AUTHORS
Requires-Dist: urwid
Requires-Dist: fuzzyfinder
Requires-Dist: atomicwrites
Requires-Dist: pyxdg
Requires-Dist: Pygments
